ginpar/__init__.py
ginpar/__main__.py
ginpar/build.py
ginpar/cli.py
ginpar/generators.py
ginpar/init.py
ginpar/new.py
ginpar/quickstart.py
ginpar/serve.py
ginpar/templates/dimensions.html
ginpar/templates/input.html
ginpar/templates/retrieve.js
ginpar/templates/sketch/data.yaml
ginpar/templates/sketch/sketch.js
ginpar/utils/__init__.py
ginpar/utils/echo.py
ginpar/utils/files.py
ginpar/utils/git.py
ginpar/utils/strings.py
tests/__init__.py
tests/test_build.py
tests/test_init.py
tests/test_new.py
tests/test_quickstart.py
ginpar-1.0.1.dist-info/LICENSE
ginpar-1.0.1.dist-info/METADATA
ginpar-1.0.1.dist-info/WHEEL
ginpar-1.0.1.dist-info/entry_points.txt
ginpar-1.0.1.dist-info/top_level.txt
ginpar-1.0.1.dist-info/RECORD
