Metadata-Version: 2.1
Name: ginpar
Version: 1.0.1
Summary: A static content generator for interactive and parametrisable p5.js canvases.
Home-page: https://github.com/davidomarf/ginpar
Author: David Omar Flores Chávez
Author-email: david@davidomar.com
License: MIT
Platform: UNKNOWN
Classifier: Programming Language :: Python :: 3
Classifier: License :: OSI Approved :: MIT License
Classifier: Operating System :: OS Independent
Requires-Dist: jinja2 (>=2.7)
Requires-Dist: pyyaml
Requires-Dist: click
Requires-Dist: livereload
